{
"Афганістан": [],
"Аландські острови": [],
"Албанія": [],
"Алжир": [],
"Американське Самоа": [],
"Андорра": [],
"Ангола": [],
"Ангілья": [],
"Антарктика": [],
"Антигуа і Барбуда": [],
"Аргентина": [],
"Вірменія": [],
"Аруба": [],
"Австралія": [],
"Австрія": [],
"Азербайджан": [],
"Багамські острови": [],
"Бахрейн": [],
"Бангладеш": [],
"Барбадос": [],
"Білорусія": [],
"Бельгія": [],
"Беліз": [],
"Бенін": [],
"Бермудські острови": [],
"Бутан": [],
"Болівія": [],
"Бонейр Сінт-Естатіус і Саба": [],
"Боснія та Герцеговина": [],
"Ботсвана": [],
"Острів Буве": [],
"Бразилія": [],
"Британська Територія в Індійському Океані": [],
"Бруней": [],
"Болгарія": [],
"Буркіна-Фасо": [],
"Бурунді": [],
"Кабо-Верде": [],
"Камбоджа": [],
"Камерун": [],
"Канада": [],
"Острови Кайман": [],
"Центральноафриканська Республіка": [],
"Чад": [],
"Чилі": [],
"Китай": [],
"Острів Різдва": [],
"Кокосові острови": [],
"Колумбія": [],
"Коморські Острови": [],
"Республіка Конго": [],
"Конго": [],
"Острови Кука": [],
"Коста-Ріка": [],
"Кот-Д'івуар": [],
"Хорватія": [],
"Куба": [],
"Кюрасао": [],
"Кіпр": [],
"Чехія": [],
"Данія": [],
"Джибуті": [],
"Домініка": [],
"Домініканська Республіка": [],
"Еквадор": [],
"Єгипет": [],
"Сальвадор": [],
"Екваторіальна Гвінея": [],
"Еритрея": [],
"Естонія": [],
"Ефіопія": [],
"Фолклендські острови": [],
"Фарерські острови": [],
"Фіджі": [],
"Фінляндія": [],
"Франція": [],
"Французька Гвіана": [],
"Французька Полінезія": [],
"Французькі Південні території": [],
"Габон": [],
"Гамбія": [],
"Грузія": [],
"Німеччина": [],
"Гана": [],
"Гібралтар": [],
"Греція": [],
"Гренландія": [],
"Гренада": [],
"Гваделупа": [],
"Гуам": [],
"Гватемала": [],
"Гернсі": [],
"Гвінея": [],
"Гвінея-Бісау": [],
"Гайана": [],
"Гаїті": [],
"Острів Херд і острови Макдональд": [],
"Ватикан": [],
"Гондурас": [],
"Гонконг": [],
"Угорщина": [],
"Ісландія": [],
"Індія": [],
"Індонезія": [],
"Іран": [],
"Ірак": [],
"Ірландія": [],
"Острів Мен": [],
"Ізраїль": [],
"Італія": [],
"Ямайка": [],
"Японія": [],
"Джерсі": [],
"Йорданія": [],
"Казахстан": [],
"Кенія": [],
"Кірібаті": [],
"Північна Корея": [],
"Південна Корея": [],
"Кувейт": [],
"Киргизстан": [],
"Лаос": [],
"Латвія": [],
"Ліван": [],
"Лесото": [],
"Ліберія": [],
"Лівія": [],
"Ліхтенштейн": [],
"Литва": [],
"Люксембург": [],
"Макао": [],
"Македонія": [],
"Мадагаскар": [],
"Малаві": [],
"Малайзія": [],
"Мальдіви": [],
"Малі": [],
"Мальта": [],
"Маршаллові Острови": [],
"Мартініка": [],
"Мавританія": [],
"Маврикій": [],
"Майотта": [],
"Мексика": [],
"Мікронезія": [],
"Молдова": [],
"Монако": [],
"Монголія": [],
"Чорногорія": [],
"Монсеррат": [],
"Марокко": [],
"Мозамбік": [],
"М'янма": [],
"Намібія": [],
"Науру": [],
"Непал": [],
"Нідерланди": [],
"Нова Каледонія": [],
"Нова Зеландія": [],
"Нікарагуа": [],
"Нігер": [],
"Нігерія": [],
"Ніуе": [],
"Острів Норфолк": [],
"Північні Маріанські Острови": [],
"Норвегія": [],
"Оман": [],
"Пакистан": [],
"Палау": [],
"Палестина": [],
"Панама": [],
"Папуа - Нова Гвінея": [],
"Парагвай": [],
"Перу": [],
"Філіппіни": [],
"Острови Піткерн": [],
"Польща": [],
"Португалія": [],
"Пуерто-Ріко": [],
"Катар": [],
"Реюньон": [],
"Румунія": [],
"Російська Федерація": [],
"Руанда": [],
"Сен-Бартелемі": [],
"Острови Святої Єлени Вознесіння і Трістан-да-Кунья": [],
"Сент-Кітс і Невіс": [],
"Сент-Люсія": [],
"Сен-Мартен": [],
"Сен-П'єр і Мікелон": [],
"Сент-Вінсент і Гренадіни": [],
"Самоа": [],
"Сан-Марино": [],
"Сан-Томе і Прінсіпі": [],
"Саудівська Аравія": [],
"Сенегал": [],
"Сербія": [],
"Сейшельські Острови": [],
"Сьєрра-Леоне": [],
"Сінгапур": [],
"Сінт-Мартен": [],
"Словаччина": [],
"Словенія": [],
"Соломонові Острови": [],
"Сомалі": [],
"Південно-Африканська Республіка": [],
"Південна Георгія і Південні Сандвічеві Острови": [],
"Південний Судан": [],
"Іспанія": [],
"Шрі-Ланка": [],
"Судан": [],
"Сурінам": [],
"Шпіцберген і Ян-Маєн": [],
"Свазіленд": [],
"Швеція": [],
"Швейцарія": [],
"Сирія": [],
"Китайська Республіка": [],
"Таджикистан": [],
"Танзанія": [],
"Таїланд": [],
"Східний Тимор": [],
"Того": [],
"Токелау": [],
"Тонга": [],
"Тринідад і Тобаго": [],
"Туніс": [],
"Туреччина": [],
"Туркменістан": [],
"Теркс і Кайкос": [],
"Тувалу": [],
"Уганда": [],
"Україна": [],
"ОАЕ": [],
"Великобританія": [],
"США": [],
"Зовнішні малі острови США": [],
"Уругвай": [],
"Узбекистан": [],
"Вануату": [],
"Венесуела": [],
"В'єтнам": [],
"Британські Віргінські острови": [],
"Віргінські острови США": [],
"Уолліс і Футуна": [],
"Західна Сахара": [],
"Ємен": [],
"Замбія": [],
"Зімбабве": []
}